[
  { "id": "lan_001", "eu": "Lana", "es": "Trabajo", "example_eu": "Nire lana oso interesgarria da.", "example_es": "Mi trabajo es muy interesante." },
  { "id": "lan_002", "eu": "Ikaslea", "es": "Estudiante", "example_eu": "Unibertsitateko ikaslea naiz.", "example_es": "Soy estudiante universitario." },
  { "id": "lan_003", "eu": "Irakaslea", "es": "Profesor/a", "example_eu": "Nire ama irakaslea da.", "example_es": "Mi madre es profesora." },
  { "id": "lan_004", "eu": "Medikua", "es": "Médico/a", "example_eu": "Nire aita medikua da.", "example_es": "Mi padre es médico." },
  { "id": "lan_005", "eu": "Ingeniarua", "es": "Ingeniero/a", "example_eu": "Ingeniarua izateko ikasten ari naiz.", "example_es": "Estudio para ser ingeniero." },
  { "id": "lan_006", "eu": "Abokatu", "es": "Abogado/a", "example_eu": "Abokatua oso lan ona da.", "example_es": "Ser abogado es un buen trabajo." },
  { "id": "lan_007", "eu": "Sukaldaria", "es": "Cocinero/a", "example_eu": "Sukaldari bikaina da.", "example_es": "Es un cocinero excelente." },
  { "id": "lan_008", "eu": "Erizaina", "es": "Enfermero/a", "example_eu": "Erizaina lan gogorra da.", "example_es": "Ser enfermero es un trabajo duro." },
  { "id": "lan_009", "eu": "Arkitektoa", "es": "Arquitecto/a", "example_eu": "Arkitekto ezagun bat da.", "example_es": "Es un arquitecto conocido." },
  { "id": "lan_010", "eu": "Langilea", "es": "Trabajador/a", "example_eu": "Langile ona da.", "example_es": "Es un buen trabajador." },
  { "id": "lan_011", "eu": "Enpresa", "es": "Empresa", "example_eu": "Enpresa handi batean lan egiten dut.", "example_es": "Trabajo en una empresa grande." },
  { "id": "lan_012", "eu": "Bulegoa", "es": "Oficina", "example_eu": "Bulegoan lan egiten dut.", "example_es": "Trabajo en una oficina." },
  { "id": "lan_013", "eu": "Unibertsitatea", "es": "Universidad", "example_eu": "Unibertsitatean ikasten dut.", "example_es": "Estudio en la universidad." },
  { "id": "lan_014", "eu": "Eskola", "es": "Escuela / Colegio", "example_eu": "Eskolan irakaslea naiz.", "example_es": "Soy profesor en el colegio." },
  { "id": "lan_015", "eu": "Zer egiten duzu?", "es": "¿A qué te dedicas?", "example_eu": "Zer egiten duzu lan gisa?", "example_es": "¿A qué te dedicas laboralmente?" },
  { "id": "lan_016", "eu": "Lan egiten dut", "es": "Trabajo", "example_eu": "Ospitalean lan egiten dut.", "example_es": "Trabajo en el hospital." },
  { "id": "lan_017", "eu": "Ikasten dut", "es": "Estudio", "example_eu": "Medikuntza ikasten dut.", "example_es": "Estudio medicina." },
  { "id": "lan_018", "eu": "Non lan egiten duzu?", "es": "¿Dónde trabajas?", "example_eu": "Non lan egiten duzu?", "example_es": "¿Dónde trabajas?" },
  { "id": "lan_019", "eu": "Zenbat ordutan hasten zara?", "es": "¿A qué hora empiezas?", "example_eu": "Zenbat ordutan hasten zara lanean?", "example_es": "¿A qué hora empiezas a trabajar?" },
  { "id": "lan_020", "eu": "Bederatzitan hasten naiz", "es": "Empiezo a las nueve", "example_eu": "Goizeko bederatzitan hasten naiz.", "example_es": "Empiezo a las nueve de la mañana." },
  { "id": "lan_021", "eu": "Oporrak", "es": "Vacaciones", "example_eu": "Oporrak abuztuan hartzen ditut.", "example_es": "Cojo las vacaciones en agosto." },
  { "id": "lan_022", "eu": "Soldata", "es": "Salario", "example_eu": "Nire soldata ona da.", "example_es": "Mi salario es bueno." },
  { "id": "lan_023", "eu": "Bilera", "es": "Reunión", "example_eu": "Bilerak astelehen guztietan ditut.", "example_es": "Tengo reuniones todos los lunes." },
  { "id": "lan_024", "eu": "Proiektua", "es": "Proyecto", "example_eu": "Proiektu berri baten lanean ari naiz.", "example_es": "Estoy trabajando en un proyecto nuevo." },
  { "id": "lan_025", "eu": "Azterketa", "es": "Examen", "example_eu": "Bihar azterketa dut.", "example_es": "Mañana tengo examen." },
  { "id": "lan_026", "eu": "Etxeko lana", "es": "Deberes / Tarea", "example_eu": "Etxeko lana egin duzu?", "example_es": "¿Has hecho los deberes?" },
  { "id": "lan_027", "eu": "Ikastola", "es": "Ikastola (escuela en euskera)", "example_eu": "Ikastolan ikasi nuen txikitatik.", "example_es": "Estudié en la ikastola desde pequeño." },
  { "id": "lan_028", "eu": "Nota", "es": "Nota / Calificación", "example_eu": "Azterketan nota ona atera dut.", "example_es": "He sacado buena nota en el examen." },
  { "id": "lan_029", "eu": "Lan bila nabil", "es": "Estoy buscando trabajo", "example_eu": "Lan bila nabil oraindik.", "example_es": "Todavía estoy buscando trabajo." },
  { "id": "lan_030", "eu": "Lanpetuta nago", "es": "Estoy ocupado/a", "example_eu": "Gaur oso lanpetuta nago.", "example_es": "Hoy estoy muy ocupado." },
  { "id": "lan_031", "eu": "Erretiroa", "es": "Jubilación", "example_eu": "Nire aitak erretiroa hartu du.", "example_es": "Mi padre se ha jubilado." }
]
